gym_jass/__init__.py
gym_jass/envs/__init__.py
gym_jass/envs/differenzler_env.py
gym_jass/envs/game_server.py
gym_jass/envs/schieber_env.py
gym_jass/envs/sidi_barani_env.py
gym_jass/envs/tournament_server.py
gym_jass/envs/toy_env.py
gym_jass-0.1.19.dist-info/METADATA
gym_jass-0.1.19.dist-info/RECORD
gym_jass-0.1.19.dist-info/WHEEL
gym_jass-0.1.19.dist-info/top_level.txt
tests/__init__.py
tests/test_schieber_env.py
