Metadata-Version: 2.1
Name: gym-jass
Version: 0.1.19
Summary: A gym environment for the Schieber variant of the Swiss card game Jass
Home-page: https://github.com/JoelNiklaus/gym-jass
Author: Joel Niklaus
Author-email: me@joelniklaus.ch
License: MIT License
Requires-Dist: gym (>=0.10.8)
Requires-Dist: schieber (>=0.1.8)
